odoo/addons/ssi_partner_identification_portal/README.rst
odoo/addons/ssi_partner_identification_portal/__init__.py
odoo/addons/ssi_partner_identification_portal/__manifest__.py
odoo/addons/ssi_partner_identification_portal/controllers/__init__.py
odoo/addons/ssi_partner_identification_portal/controllers/portal.py
odoo/addons/ssi_partner_identification_portal/models/__init__.py
odoo/addons/ssi_partner_identification_portal/models/portal_identification_number.py
odoo/addons/ssi_partner_identification_portal/security/ir.model.access.csv
odoo/addons/ssi_partner_identification_portal/security/ir_rule_data.xml
odoo/addons/ssi_partner_identification_portal/static/description/icon.png
odoo/addons/ssi_partner_identification_portal/static/src/scss/portal.scss
odoo/addons/ssi_partner_identification_portal/views/assets.xml
odoo/addons/ssi_partner_identification_portal/views/portal_templates.xml
odoo14_addon_ssi_partner_identification_portal-14.0.1.0.1.dev6.dist-info/METADATA
odoo14_addon_ssi_partner_identification_portal-14.0.1.0.1.dev6.dist-info/WHEEL
odoo14_addon_ssi_partner_identification_portal-14.0.1.0.1.dev6.dist-info/top_level.txt
odoo14_addon_ssi_partner_identification_portal-14.0.1.0.1.dev6.dist-info/RECORD
